charylutokenizer/__init__.py
charylutokenizer/charylutokenizer.py
charylutokenizer/create_tokenizer.py
charylutokenizer/load.py
charylutokenizer/artifacts/charylu/tokenizer_2024_100k.json
charylutokenizer/artifacts/charylu/tokenizer_2024_120k.json
charylutokenizer/artifacts/charylu/tokenizer_2024_150k.json
charylutokenizer/artifacts/charylu/tokenizer_2024_32k.json
charylutokenizer/artifacts/charylu/tokenizer_2024_50k.json
charylutokenizer/artifacts/charylu/tokenizer_2024_60k.json
charylutokenizer/artifacts/charylu/tokenizer_2024_70k.json
charylutokenizer/artifacts/charylu/tokenizer_2024_80k.json
charylutokenizer/artifacts/charylu/tokenizer_2024_90k.json
charylutokenizer/artifacts/charylu_nocode/tokenizer_2024_100k.json
charylutokenizer/artifacts/charylu_nocode/tokenizer_2024_110k.json
charylutokenizer/artifacts/charylu_nocode/tokenizer_2024_120k.json
charylutokenizer/artifacts/charylu_nocode/tokenizer_2024_130k.json
charylutokenizer/artifacts/charylu_nocode/tokenizer_2024_150k.json
charylutokenizer/artifacts/charylu_nocode/tokenizer_2024_32k.json
charylutokenizer/artifacts/charylu_nocode/tokenizer_2024_50k.json
charylutokenizer/artifacts/charylu_nocode/tokenizer_2024_60k.json
charylutokenizer/artifacts/charylu_nocode/tokenizer_2024_70k.json
charylutokenizer/artifacts/charylu_nocode/tokenizer_2024_80k.json
charylutokenizer/artifacts/charylu_nocode/tokenizer_2024_90k.json
charylu_tokenizer-0.0.5.dist-info/LICENSE.txt
charylu_tokenizer-0.0.5.dist-info/METADATA
charylu_tokenizer-0.0.5.dist-info/WHEEL
charylu_tokenizer-0.0.5.dist-info/top_level.txt
charylu_tokenizer-0.0.5.dist-info/RECORD
